{
  "synergy": [],
  "props": {
    "altMode": true,
    "lock": -1
  },
  "gameplayDesc": "U31_SKIN4_DESC",
  "moneyCost": 0,
  "group": 13,
  "castCD": 0,
  "id": "Mentor3",
  "icon": {
    "x": 33,
    "y": 17,
    "file": "cardIcons.png",
    "size": 24
  },
  "legendAffixes": [],
  "name": "U31_SKIN4_NAME",
  "droppable": true,
  "tags": [
    {
      "tag": "InstantBlueprint"
    }
  ],
  "cellCost": 1000,
  "__separator_group_ID": 13,
  "__separator_group_Name": "Skin",
  "__original_Index": 502
}