{
  "synergy": [],
  "props": {
    "speed": 1,
    "range": 15,
    "offsetX": 4,
    "offsetY": 1,
    "height": 20,
    "distance": 60
  },
  "gameplayDesc": "U32_STARFURY_GAMEPLAYDESC",
  "moneyCost": 2000,
  "group": 4,
  "castCD": 0,
  "ambiantDesc": "U32_STARFURY_AMBIENTDESC",
  "id": "Starfury",
  "icon": {
    "x": 34,
    "y": 4,
    "file": "cardIcons.png",
    "size": 24
  },
  "legendAffixes": [
    {
      "affix": "DoubleBullets"
    }
  ],
  "name": "U32_STARFURY_NAME",
  "droppable": true,
  "tags": [],
  "tier1": "Brutality",
  "tier2": "Tactic",
  "cellCost": 50,
  "__separator_group_ID": 4,
  "__separator_group_Name": "Melee",
  "__original_Index": 142
}