{
  "id": "Mage360",
  "score": 5,
  "canBeElite": true,
  "minPfSize": 3,
  "maxPerRoom": 3,
  "props": {
    "directHitStunChance": 1,
    "movePauseMul": 0,
    "moveSpeedMul": 0.5
  },
  "skill": [
    {
      "id": "shoot",
      "charge": 0.7,
      "coolDown": 0.15,
      "power": [
        8
      ],
      "props": {
        "canTriggerThroughWall": true
      },
      "lockAiAfter": 0,
      "radius": 0,
      "allowSameSkillNearby": false,
      "ignoreGlobalCD": false,
      "breachResistance": -10,
      "allowInAir": false,
      "disableAnnounce": false,
      "hitFrame": 30,
      "manual": false,
      "sfxCharge": "sfx/enm_mage_charge.wav",
      "sfxRelease": "sfx/enm_mage_release.wav"
    },
    {
      "id": "dodge",
      "charge": 0,
      "coolDown": 1,
      "hitFrame": 0,
      "lockAiAfter": 0.2,
      "radius": 0,
      "breachResistance": 0,
      "disableAnnounce": false,
      "manual": false,
      "allowInAir": false,
      "allowSameSkillNearby": false,
      "ignoreGlobalCD": false,
      "props": {
        "distance": 2
      }
    }
  ],
  "genTags": 1,
  "index": 29,
  "group": 0,
  "name": "Inquisiteur",
  "life": [
    100
  ],
  "weight": 15,
  "glowInnerColor": 7819992,
  "volteDelay": 0.7,
  "flesh1": 15659003,
  "flesh2": 15147554,
  "pfCost": 1.7,
  "icon": {
    "file": "cardIcons.png",
    "size": 24,
    "x": 46,
    "y": 78
  },
  "blueprints": [
    {
      "chance": 0.05,
      "item": "Lightning"
    }
  ],
  "cellChance": 0.5,
  "cells": [
    1,
    2
  ],
  "__separator_group_ID": 0,
  "__separator_group_Name": "General",
  "__original_Index": 29
}