{
  "id": "T_Courtyard",
  "biome": "PrisonCourtyard",
  "mobs": [],
  "mobDensity": 0,
  "eliteWanderChance": 0,
  "eliteRoomChance": 0,
  "flags": 0,
  "lootFlags": 27,
  "specificLoots": [],
  "goldBonus": 0,
  "group": 1,
  "transitionTo": "PrisonCourtyard",
  "index": 25,
  "cellBonus": 0,
  "tripleUps": 0,
  "doubleUps": 0,
  "props": {
    "viewerY": 0.75,
    "musicLoop": "music/dc_colletor2.ogg",
    "loadingColor": 598322,
    "loadingDescColor": 6652612,
    "timedDoor": 2,
    "timedBlueprint": "DashShield",
    "perfectKillsDoor": 0.5,
    "zDoorColor": 15637011
  },
  "specificSubBiome": [],
  "baseLootLevel": 2,
  "worldDepth": 0,
  "loreDescriptions": [],
  "name": "Passage vers la Promenade des condamnés",
  "quarterUpsBC3": 0,
  "quarterUpsBC4": 0,
  "__separator_group_ID": 1,
  "__separator_group_Name": "Transition",
  "__original_Index": 25
}