{
  "allowCrouch": false,
  "isACancel": false,
  "item": "ThrowingKnife",
  "strikeChain": [
    {
      "coolDown": 0.25,
      "power": [
        5
      ],
      "fxProps": {
        "fxInnerColor": 13094115,
        "fxStartFrame": 2,
        "fxOuterColor": 13094115
      },
      "lockCtrlAfter": 0,
      "props": {},
      "breachBonus": -1,
      "dynamicCharge": 0,
      "charge": 0.1,
      "sfxProps": {},
      "canCrit": false,
      "area": {
        "width": 0,
        "offsetCaseX": 0,
        "offsetCaseY": 0,
        "height": 0,
        "shape": 0
      },
      "sfxRelease": "sfx/weapon_kunai_release.wav",
      "fxId": "fxThrow",
      "animId": "throw",
      "hitFrame": 5,
      "glowColor": 13094115
    }
  ],
  "airControlAlways": true,
  "cannotBeCanceledByWeapon": false,
  "__separator_group_ID": -1,
  "__separator_group_Name": "",
  "__original_Index": 64
}