{
  "props": {
    "prct": 0.15,
    "duration": 1.5
  },
  "gameplayDesc": "Restitue ::prct::% de votre santé.",
  "moneyCost": 0,
  "group": 10,
  "castCD": 0,
  "id": "SmallCastlevania",
  "icon": {
    "x": 19,
    "y": 3,
    "file": "cardIcons.png",
    "size": 24
  },
  "name": "Patisserie",
  "droppable": false,
  "tags": [
    {
      "tag": "SmallHealConsumable"
    }
  ],
  "cellCost": 0,
  "__separator_group_ID": 10,
  "__separator_group_Name": "Consumable",
  "__original_Index": 237
}