{
  "id": "PrisonCourtyard",
  "biome": "PrisonCourtyard2",
  "mobs": [
    {
      "mob": "Zombie",
      "quantityFactor": 4,
      "singleRoom": false,
      "minCombatRoomsBefore": 0,
      "props": {}
    },
    {
      "mob": "BatDasher",
      "quantityFactor": 3,
      "singleRoom": false,
      "minCombatRoomsBefore": 0,
      "props": {}
    },
    {
      "mob": "Grenader",
      "quantityFactor": 4,
      "singleRoom": false,
      "minCombatRoomsBefore": 0,
      "props": {}
    },
    {
      "mob": "Runner",
      "quantityFactor": 2,
      "singleRoom": false,
      "minCombatRoomsBefore": 0,
      "props": {}
    },
    {
      "mob": "Shielder",
      "quantityFactor": 1,
      "singleRoom": false,
      "minCombatRoomsBefore": 1,
      "props": {}
    }
  ],
  "mobDensity": 1.1,
  "eliteWanderChance": 0.5,
  "eliteRoomChance": 0,
  "viewerY": 0.75,
  "flags": 1,
  "lootFlags": 0,
  "specificLoots": [],
  "goldBonus": 0,
  "group": 0,
  "name": "Promenade des condamnés",
  "doorColor": 65490,
  "musicLoop": "music/Promenade.ogg",
  "index": 1,
  "lootLevel": 2,
  "zDoorColor": 15637011,
  "viewerOffX": 0,
  "cellBonus": 0,
  "viewerColor": 6666220,
  "chromaColor": 65490,
  "tripleUps": 1,
  "doubleUps": 2,
  "extraMobTier": 1,
  "baseMobTier": 2,
  "props": {
    "timedDoor": 3.25,
    "timedBlueprint": "DashShield"
  },
  "__separator_group_ID": 0,
  "__separator_group_Name": "MainLevels",
  "__original_Index": 1
}