{
  "id": "P_SpeedHeal",
  "name": "Frénésie",
  "moneyCost": 0,
  "cellCost": 50,
  "droppable": true,
  "castCD": 0,
  "tags": [],
  "props": {
    "prct": 1.2E-05,
    "customScaling": 1.055,
    "scaledValueCap": 8E-05
  },
  "group": 12,
  "icon": {
    "file": "cardIcons.png",
    "size": 24,
    "x": 4,
    "y": 14
  },
  "tier1": "Brutality",
  "gameplayDesc": "Vos attaques au corps à corps vous font récupérer une petite portion de vos PV en fonction des dégats infligés tant que votre vitesse est augmentée.",
  "__separator_group_ID": 12,
  "__separator_group_Name": "Perk",
  "__original_Index": 253
}